bandipy/__init__.py
bandipy-0.0.1.dist-info/LICENSE
bandipy-0.0.1.dist-info/METADATA
bandipy-0.0.1.dist-info/WHEEL
bandipy-0.0.1.dist-info/top_level.txt
bandipy-0.0.1.dist-info/RECORD
